calibre_recipe_runner/__init__.py
calibre_recipe_runner/cli.py
calibre_recipe_runner/get-recipes.sh
calibre_recipe_runner/stubs.py
calibre_recipe_runner-0.1.0.dist-info/licenses/LICENSE
calibre_recipe_runner-0.1.0.dist-info/METADATA
calibre_recipe_runner-0.1.0.dist-info/WHEEL
calibre_recipe_runner-0.1.0.dist-info/entry_points.txt
calibre_recipe_runner-0.1.0.dist-info/top_level.txt
calibre_recipe_runner-0.1.0.dist-info/RECORD
