Metadata-Version: 2.4
Name: calibre-recipe-runner
Version: 0.1.0
Summary: A lightweight Python sandbox for running Calibre news recipes.
Author-email: Stefan Pernes <stefan@pernes.net>
License: MIT
License-File: LICENSE
Requires-Dist: beautifulsoup4
Requires-Dist: feedparser
Requires-Dist: requests
Requires-Dist: python-dateutil
Dynamic: license-file
